LICENSE
MANIFEST.in
README.rst
rswt_flasher.py
setup.py
rswt_flasher.egg-info/PKG-INFO
rswt_flasher.egg-info/SOURCES.txt
rswt_flasher.egg-info/dependency_links.txt
rswt_flasher.egg-info/entry_points.txt
rswt_flasher.egg-info/requires.txt
rswt_flasher.egg-info/top_level.txt