Metadata-Version: 1.1
Name: rswt-flasher
Version: 0.1.0
Summary: Firmware upload utility for a RobertSonics WavTrigger.
Home-page: https://github.com/wayoda/rswt-flasher/
Author: Eberhard Fahle
Author-email: e.fahle@wayoda.org
License: MIT
Platform: UNKNOWN
Classifier: Development Status :: 4 - Beta
Classifier: Intended Audience :: Developers
Classifier: Natural Language :: English
Classifier: License :: OSI Approved :: MIT License
Classifier: Operating System :: OS Independent
Classifier: Programming Language :: Python
Classifier: Programming Language :: Python :: 2
Classifier: Programming Language :: Python :: 2.7
Classifier: Programming Language :: Python :: 3
Classifier: Programming Language :: Python :: 3.3
Classifier: Programming Language :: Python :: 3.4
Classifier: Topic :: Utilities
Classifier: Topic :: Multimedia :: Sound/Audio :: Players
